{"__symbolic":"module","version":3,"metadata":{"Ng2FlatpickrComponent":{"__symbolic":"class","decorators":[{"__symbolic":"call","expression":{"__symbolic":"reference","module":"@angular/core","name":"Component"},"arguments":[{"selector":"ng2-flatpickr","template":"\n\t\t<div class=\"ng2-flatpickr-input-container\" #flatpickr>\n\t\t\t<input class=\"ng2-flatpickr-input\" [placeholder]=\"placeholder\" type=\"text\" data-input>\n\t\t</div>","providers":[{"provide":{"__symbolic":"reference","module":"@angular/forms","name":"NG_VALUE_ACCESSOR"},"useExisting":{"__symbolic":"reference","name":"Ng2FlatpickrComponent"},"multi":true}]}]}],"members":{"flatpickrElement":[{"__symbolic":"property","decorators":[{"__symbolic":"call","expression":{"__symbolic":"reference","module":"@angular/core","name":"ViewChild"},"arguments":["flatpickr"]}]}],"config":[{"__symbolic":"property","decorators":[{"__symbolic":"call","expression":{"__symbolic":"reference","module":"@angular/core","name":"Input"}}]}],"placeholder":[{"__symbolic":"property","decorators":[{"__symbolic":"call","expression":{"__symbolic":"reference","module":"@angular/core","name":"Input"}}]}],"setDate":[{"__symbolic":"property","decorators":[{"__symbolic":"call","expression":{"__symbolic":"reference","module":"@angular/core","name":"Input"}}]}],"writeValue":[{"__symbolic":"method"}],"registerOnChange":[{"__symbolic":"method"}],"registerOnTouched":[{"__symbolic":"method"}],"setDateFromInput":[{"__symbolic":"method"}],"ngAfterViewInit":[{"__symbolic":"method"}],"ngOnChanges":[{"__symbolic":"method"}]}},"FlatpickrOptions":{"__symbolic":"interface"},"Ng2FlatpickrModule":{"__symbolic":"class","decorators":[{"__symbolic":"call","expression":{"__symbolic":"reference","module":"@angular/core","name":"NgModule"},"arguments":[{"declarations":[{"__symbolic":"reference","name":"Ng2FlatpickrComponent"}],"exports":[{"__symbolic":"reference","name":"Ng2FlatpickrComponent"}],"imports":[{"__symbolic":"reference","module":"@angular/forms","name":"FormsModule"},{"__symbolic":"reference","module":"@angular/forms","name":"ReactiveFormsModule"}]}]}],"members":{}}},"origins":{"Ng2FlatpickrComponent":"./src/ng2-flatpickr.component","FlatpickrOptions":"./src/flatpickr-options.interface","Ng2FlatpickrModule":"./src/ng2-flatpickr.module"},"importAs":"ng2-flatpickr"}